{
    "php.validate.executablePath": "/opt/lampp/bin/php",
    "editor.fontSize": 12,
    "editor.fontLigatures": true,
    "editor.fontFamily": "'Fira Code', 'Droid Sans Mono', 'monospace', monospace, 'Droid Sans Fallback'",
    "terminal.integrated.fontFamily": "'Fira Code', 'Droid Sans Mono', 'monospace', monospace, 'Droid Sans Fallback'",
    "files.autoSave": "afterDelay",
    "workbench.editor.highlightModifiedTabs": true,
    "workbench.iconTheme": "vscode-icons",
    "workbench.settings.editor": "json",
    "python.jediEnabled": false,
    "editor.rulers": [
        80,
        120
    ],
    "git.autofetch": true,
    "npm.packageManager": "yarn",
    "prettier.packageManager": "yarn",
    "window.menuBarVisibility": "toggle",
    "editor.wordWrap": "off",
    "editor.suggestSelection": "first",
    "vsintellicode.modify.editor.suggestSelection": "automaticallyOverrodeDefaultValue",
    "java.configuration.checkProjectSettingsExclusions": false,
    "editor.acceptSuggestionOnEnter": "off",
    "editor.formatOnPaste": false,
    "editor.formatOnSave": true,
    "eslint.run": "onSave",
    // suggestions from Shades of Purple
    "editor.cursorBlinking": "phase",
    "editor.renderWhitespace": "all",
    "editor.snippetSuggestions": "top",
    "workbench.editor.enablePreview": false,
    "explorer.confirmDragAndDrop": false,
    "files.trimTrailingWhitespace": true,
    "files.trimFinalNewlines": true,
    "diffEditor.ignoreTrimWhitespace": false,
    "workbench.colorTheme": "One Dark Pro",
    "java.semanticHighlighting.enabled": true,
    "emmet.includeLanguages": {
        "javascript": "javascriptreact"
    },
    "[javascript]": {
        "editor.defaultFormatter": "esbenp.prettier-vscode"
    },
    "javascript.updateImportsOnFileMove.enabled": "always"
}
